cubicweb_saml/__init__.py
cubicweb_saml/__pkginfo__.py
cubicweb_saml/pconfig.py
cubicweb_saml/site_cubicweb.py
cubicweb_saml/utils.py
cubicweb_saml/views.py
cubicweb_saml/i18n/en.po
cubicweb_saml/i18n/es.po
cubicweb_saml/i18n/fr.po
cubicweb_saml/migration/postcreate.py
cubicweb_saml-1.0.1.dist-info/METADATA
cubicweb_saml-1.0.1.dist-info/WHEEL
cubicweb_saml-1.0.1.dist-info/entry_points.txt
cubicweb_saml-1.0.1.dist-info/top_level.txt
cubicweb_saml-1.0.1.dist-info/RECORD
