Metadata-Version: 2.1
Name: cubicweb-saml
Version: 1.0.1
Summary: SAML2 authentifier
Home-page: https://forge.extranet.logilab.fr/cubicweb/cubes/cubicweb-saml
Author: LOGILAB S.A. (Paris, FRANCE)
Author-email: contact@logilab.fr
License: LGPL
Classifier: Environment :: Web Environment
Classifier: Framework :: CubicWeb
Classifier: Programming Language :: Python
Requires-Dist: cubicweb <5.0.0,>=4.0.0
Requires-Dist: cubicweb-web <2.0.0,>=1.0.0
Requires-Dist: logilab-common >=1.4.0
Requires-Dist: pyramid >=1.10.4
Requires-Dist: pysaml2 >=5.0.0
Requires-Dist: requests >=2.22.0
Requires-Dist: zope.interface >=4.1.2
